model_compiler_for_papyrusrt/__init__.py
model_compiler_for_papyrusrt/__main__.py
model_compiler_for_papyrusrt/application.py
model_compiler_for_papyrusrt/build_configuration/__init__.py
model_compiler_for_papyrusrt/build_configuration/build_configuration.py
model_compiler_for_papyrusrt/build_configuration/top_build_configuration.py
model_compiler_for_papyrusrt/generator/__init__.py
model_compiler_for_papyrusrt/generator/papyrusrt_codegen_wrapper.py
model_compiler_for_papyrusrt/generator/target_specific_cmakelists_generator.py
model_compiler_for_papyrusrt/generator/target_specific_generator.py
model_compiler_for_papyrusrt/generator/top_cmakelists_generator.py
model_compiler_for_papyrusrt/generator/top_generator.py
model_compiler_for_papyrusrt/misc/dummy_cmakelists_generator.py
model_compiler_for_papyrusrt-1.0.0.dist-info/METADATA
model_compiler_for_papyrusrt-1.0.0.dist-info/WHEEL
model_compiler_for_papyrusrt-1.0.0.dist-info/top_level.txt
model_compiler_for_papyrusrt-1.0.0.dist-info/RECORD
